django_assets_manager/__init__.py
django_assets_manager/apps.py
django_assets_manager/checks.py
django_assets_manager/finders.py
django_assets_manager/settings.py
django_assets_manager/utils.py
django_assets_manager/management/__init__.py
django_assets_manager/management/commands/__init__.py
django_assets_manager/management/commands/compilesprites.py
django_assets_manager/templates/assets_manager/css.html
django_assets_manager/templates/assets_manager/js.html
django_assets_manager/templatetags/__init__.py
django_assets_manager/templatetags/assets_manager.py
django_assets_manager-1.0.0.dist-info/AUTHORS
django_assets_manager-1.0.0.dist-info/LICENSE
django_assets_manager-1.0.0.dist-info/METADATA
django_assets_manager-1.0.0.dist-info/WHEEL
django_assets_manager-1.0.0.dist-info/top_level.txt
django_assets_manager-1.0.0.dist-info/RECORD
