Metadata-Version: 2.1
Name: django-assets-manager
Version: 1.0.0
Summary: Assets management for django
Author-email: Miroslav Bendík <miroslav.bendik@gmail.com>
License: MIT
Project-URL: homepage, https://github.com/mireq/django-assets-manager
Project-URL: documentation, https://github.com/mireq/django-assets-manager
Project-URL: repository, https://github.com/mireq/django-assets-manager
Project-URL: changelog, https://github.com/mireq/django-assets-manager/blob/master/CHANGELOG.md
Keywords: django,assets,sprites
Classifier: Programming Language :: Python :: 3
Requires-Python: >=3.7
License-File: LICENSE
License-File: AUTHORS
Requires-Dist: django
Requires-Dist: pillow
Provides-Extra: dev
Requires-Dist: tox ; extra == 'dev'
Requires-Dist: pylint ; extra == 'dev'
Requires-Dist: pre-commit ; extra == 'dev'
Requires-Dist: bump2version ; extra == 'dev'
Requires-Dist: commitizen ; extra == 'dev'
Requires-Dist: django-jinja ; extra == 'dev'
